[
  {
    "model": "tressreliefapi.category",
    "pk": 1,
    "fields": {
      "name": "Braids",
      "description": "Variety of styles and creative braid options.",
      "image_url": "",
      "created_at": "2025-01-01T00:00:00Z",
      "updated_at": "2025-01-01T00:00:00Z"
    }
  },
  {
    "model": "tressreliefapi.category",
    "pk": 2,
    "fields": {
      "name": "Feedins",
      "description": "Festival-ready feed-in braids.",
      "image_url": "",
      "created_at": "2025-01-01T00:00:00Z",
      "updated_at": "2025-01-01T00:00:00Z"
    }
  },
  {
    "model": "tressreliefapi.category",
    "pk": 3,
    "fields": {
      "name": "Tinsel",
      "description": "Sparkling hair tinsel for everyday glam or special events.",
      "image_url": "",
      "created_at": "2025-01-01T00:00:00Z",
      "updated_at": "2025-01-01T00:00:00Z"
    }
  },
  {
    "model": "tressreliefapi.category",
    "pk": 4,
    "fields": {
      "name": "Parties",
      "description": "Braid and tinsel services for celebrations and events. Bachelorettes, birthdays, or just because parties!",
      "image_url": "",
      "created_at": "2025-01-01T00:00:00Z",
      "updated_at": "2025-01-01T00:00:00Z"
    }
  }
]
